[{"number":1.0,"nome":"djdj"},{"number":2.0,"nome":"eueu"},{"number":3.0,"nome":"Adaptive"},{"number":4.0,"nome":"Bottom App Bar"},{"number":5.0,"nome":"Bottom Sheet"},{"number":6.0,"nome":"Buttons"},{"number":7.0,"nome":"Cards"},{"number":8.0,"nome":"Carousel"},{"number":9.0,"nome":"Checkbox"},{"number":10.0,"nome":"Chips"},{"number":11.0,"nome":"Color"},{"number":12.0,"nome":"Date Picker"},{"number":13.0,"nome":"Dialogs"},{"number":14.0,"nome":"Divider"},{"number":15.0,"nome":"Elevation and Shadow"},{"number":16.0,"nome":"Floating Action Button"},{"number":17.0,"nome":"Image View"},{"number":18.0,"nome":"Menus"},{"number":19.0,"nome":"Navigation Bar (Bottom Navigation)"},{"number":20.0,"nome":"Navigation Drawer"},{"number":21.0,"nome":"Navigation Rail"},{"number":22.0,"nome":"Progress Indicator"},{"number":23.0,"nome":"Radio Button"},{"number":24.0,"nome":"Search"},{"number":25.0,"nome":"Shape Theming"},{"number":26.0,"nome":"Side Sheet"},{"number":27.0,"nome":"Shape Theming"},{"number":28.0,"nome":"Side Sheet"},{"number":29.0,"nome":"Slider"},{"number":30.0,"nome":"Switch"},{"number":31.0,"nome":"Tabs"},{"number":32.0,"nome":"Text Field"},{"number":33.0,"nome":"Time Picker"},{"number":34.0,"nome":"Top App Bar"},{"number":35.0,"nome":"Transition"},{"number":36,"nome":"Typography"}]